README.rst
setup.cfg
setup.py
socialauth/__init__.py
socialauth/authentication.py
socialauth.egg-info/PKG-INFO
socialauth.egg-info/SOURCES.txt
socialauth.egg-info/dependency_links.txt
socialauth.egg-info/requires.txt
socialauth.egg-info/top_level.txt
socialauth/providers/__init__.py
socialauth/providers/facebook.py
socialauth/providers/twitter.py