Metadata-Version: 1.1
Name: socialauth
Version: 0.2.0
Summary: A framework- and backend-independent social login provider.
Home-page: https://github.com/emilyhorsman/socialauth
Author: Emily Horsman
Author-email: me@emilyhorsman.com
License: MIT
Platform: UNKNOWN
Classifier: Development Status :: 4 - Beta
Classifier: Programming Language :: Python :: 3.3
Classifier: Programming Language :: Python :: 3.4
Classifier: Programming Language :: Python :: 3.5
